mllooper/__init__.py
mllooper/looper.py
mllooper/module.py
mllooper/run.py
mllooper/state.py
mllooper/utils.py
mllooper/data/__init__.py
mllooper/data/dataset.py
mllooper/data/dataset_loader.py
mllooper/data/datasets.py
mllooper/logging/__init__.py
mllooper/logging/handler.py
mllooper/logging/logger.py
mllooper/logging/messages.py
mllooper/metrics/__init__.py
mllooper/metrics/metric.py
mllooper/metrics/metrics.py
mllooper/models/__init__.py
mllooper/models/model.py
mllooper/models/efficientnet/__init__.py
mllooper/models/efficientnet/model.py
mllooper/models/resnet/__init__.py
mllooper/models/resnet/model.py
mllooper/state_tests/__init__.py
mllooper/state_tests/state_test.py
mllooper/state_tests/state_tests.py
mllooper/trainer/__init__.py
mllooper/trainer/optimizer.py
mllooper/trainer/scheduler.py
mllooper/trainer/trainer.py
mllooper-1.0.1.dist-info/LICENSE.txt
mllooper-1.0.1.dist-info/METADATA
mllooper-1.0.1.dist-info/WHEEL
mllooper-1.0.1.dist-info/entry_points.txt
mllooper-1.0.1.dist-info/top_level.txt
mllooper-1.0.1.dist-info/RECORD
